{"_id":"password-hash","_rev":"34-e03a79542db95d5f19193be5b524379c","name":"password-hash","description":"Password hashing and verification for node.js","dist-tags":{"latest":"1.2.2"},"versions":{"1.0.0":{"name":"password-hash","description":"Password hashing and verification for node.js","version":"1.0.0","author":{"name":"David Wood","email":"bitprobe@gmail.com"},"repository":{"type":"git","url":"git://github.com/davidwood/node-password-hash.git"},"keywords":["password","hash","utilities"],"devDependencies":{"expresso":">= 0.7"},"main":"./lib/password-hash.js","engines":{"node":">= 0.4.0"},"dependencies":{},"_id":"password-hash@1.0.0","_engineSupported":true,"_npmVersion":"1.0.5","_nodeVersion":"v0.4.7","_defaultsLoaded":true,"dist":{"shasum":"bc4264c645b9f0f2796a9334f921025246e39819","tarball":"https://registry.npmjs.org/password-hash/-/password-hash-1.0.0.tgz"},"scripts":{},"directories":{}},"1.0.1":{"name":"password-hash","description":"Password hashing and verification for node.js","version":"1.0.1","author":{"name":"David Wood","email":"bitprobe@gmail.com"},"repository":{"type":"git","url":"git://github.com/davidwood/node-password-hash.git"},"keywords":["password","hash","utilities"],"devDependencies":{"expresso":">= 0.7"},"main":"./lib/password-hash.js","engines":{"node":">= 0.4.0"},"dependencies":{},"_id":"password-hash@1.0.1","_engineSupported":true,"_npmVersion":"1.0.5","_nodeVersion":"v0.4.7","_defaultsLoaded":true,"dist":{"shasum":"a689deef2a4a987aa9aa9dd12b721b5571d22c57","tarball":"https://registry.npmjs.org/password-hash/-/password-hash-1.0.1.tgz"},"scripts":{},"directories":{}},"1.1.0":{"name":"password-hash","description":"Password hashing and verification for node.js","version":"1.1.0","author":{"name":"David Wood","email":"bitprobe@gmail.com"},"repository":{"type":"git","url":"git://github.com/davidwood/node-password-hash.git"},"keywords":["password","hash","utilities"],"devDependencies":{"expresso":">= 0.7"},"main":"./lib/password-hash.js","engines":{"node":">= 0.4.0"},"dependencies":{},"_id":"password-hash@1.1.0","_engineSupported":true,"_npmVersion":"1.0.5","_nodeVersion":"v0.4.7","_defaultsLoaded":true,"dist":{"shasum":"724ac1eb88f5ca9035e6dd6c84ea5f642f5274a8","tarball":"https://registry.npmjs.org/password-hash/-/password-hash-1.1.0.tgz"},"scripts":{},"directories":{}},"1.1.2":{"name":"password-hash","description":"Password hashing and verification for node.js","version":"1.1.2","author":{"name":"David Wood","email":"bitprobe@gmail.com"},"repository":{"type":"git","url":"git://github.com/davidwood/node-password-hash.git"},"keywords":["password","hash","utilities","cli"],"devDependencies":{"expresso":">= 0.7","colors":">=0.5.0"},"main":"./lib/password-hash.js","engines":{"node":">= 0.4.0"},"bin":{"nodepw":"./bin/nodepw"},"_npmJsonOpts":{"file":"/Users/david/.npm/password-hash/1.1.2/package/package.json","wscript":false,"contributors":false,"serverjs":false},"_id":"password-hash@1.1.2","dependencies":{},"_engineSupported":true,"_npmVersion":"1.0.22","_nodeVersion":"v0.4.7","_defaultsLoaded":true,"dist":{"shasum":"78c8d527f1373e72f9a2a535748a6b03401f8dc2","tarball":"https://registry.npmjs.org/password-hash/-/password-hash-1.1.2.tgz"},"scripts":{},"maintainers":[{"name":"davidwood","email":"bitprobe@gmail.com"}],"directories":{}},"1.1.3":{"name":"password-hash","description":"Password hashing and verification for node.js","version":"1.1.3","author":{"name":"David Wood","email":"bitprobe@gmail.com"},"repository":{"type":"git","url":"git://github.com/davidwood/node-password-hash.git"},"keywords":["password","hash","utilities","cli"],"devDependencies":{"expresso":">= 0.7","colors":">=0.5.0"},"main":"./lib/password-hash.js","engines":{"node":">= 0.4.0"},"bin":{"nodepw":"./bin/nodepw"},"_npmUser":{"name":"davidwood","email":"bitprobe@gmail.com"},"_id":"password-hash@1.1.3","dependencies":{},"_engineSupported":true,"_npmVersion":"1.0.94","_nodeVersion":"v0.4.11","_defaultsLoaded":true,"dist":{"shasum":"40d9fdf805f3069c5e59754e953fcc1edac6c68f","tarball":"https://registry.npmjs.org/password-hash/-/password-hash-1.1.3.tgz"},"maintainers":[{"name":"davidwood","email":"bitprobe@gmail.com"}],"directories":{}},"1.2.0":{"name":"password-hash","description":"Password hashing and verification for node.js","version":"1.2.0","author":{"name":"David Wood","email":"bitprobe@gmail.com"},"repository":{"type":"git","url":"git://github.com/davidwood/node-password-hash.git"},"keywords":["password","hash","utilities","cli"],"devDependencies":{"expresso":">= 0.7","colors":">=0.5.0"},"main":"./lib/password-hash.js","engines":{"node":">= 0.4.0"},"bin":{"nodepw":"./bin/nodepw"},"_npmUser":{"name":"davidwood","email":"bitprobe@gmail.com"},"_id":"password-hash@1.2.0","dependencies":{},"optionalDependencies":{},"_engineSupported":true,"_npmVersion":"1.1.18","_nodeVersion":"v0.6.15","_defaultsLoaded":true,"dist":{"shasum":"fce457a0a1af09f0f662b4ccd120f1fef706c9e9","tarball":"https://registry.npmjs.org/password-hash/-/password-hash-1.2.0.tgz"},"maintainers":[{"name":"davidwood","email":"bitprobe@gmail.com"}],"directories":{}},"1.2.1":{"name":"password-hash","description":"Password hashing and verification for node.js","version":"1.2.1","author":{"name":"David Wood","email":"bitprobe@gmail.com"},"repository":{"type":"git","url":"git://github.com/davidwood/node-password-hash.git"},"keywords":["password","hash","utilities","cli"],"devDependencies":{"expresso":">= 0.7","colors":">=0.5.0"},"main":"./lib/password-hash.js","engines":{"node":">= 0.4.0"},"bin":{"nodepw":"./bin/nodepw"},"_npmUser":{"name":"davidwood","email":"bitprobe@gmail.com"},"_id":"password-hash@1.2.1","dependencies":{},"optionalDependencies":{},"_engineSupported":true,"_npmVersion":"1.1.18","_nodeVersion":"v0.6.18","_defaultsLoaded":true,"dist":{"shasum":"90e231f193ab75ec42aaa5f779b59b8cbdcb2674","tarball":"https://registry.npmjs.org/password-hash/-/password-hash-1.2.1.tgz"},"maintainers":[{"name":"davidwood","email":"bitprobe@gmail.com"}],"directories":{}},"1.2.2":{"name":"password-hash","description":"Password hashing and verification for node.js","version":"1.2.2","author":{"name":"David Wood","email":"bitprobe@gmail.com"},"repository":{"type":"git","url":"http://github.com/davidwood/node-password-hash.git"},"keywords":["password","hash","utilities","cli"],"devDependencies":{"mocha":"*","colors":">=0.5.0"},"main":"./lib/password-hash.js","scripts":{"test":"make test"},"bin":{"nodepw":"./bin/nodepw"},"engines":{"node":">= 0.4.0"},"bugs":{"url":"https://github.com/davidwood/node-password-hash/issues"},"homepage":"https://github.com/davidwood/node-password-hash","_id":"password-hash@1.2.2","dist":{"shasum":"3b451f014de4b2e1ebfa0e5493b9517b1063af1d","tarball":"https://registry.npmjs.org/password-hash/-/password-hash-1.2.2.tgz"},"_from":".","_npmVersion":"1.4.3","_npmUser":{"name":"davidwood","email":"bitprobe@gmail.com"},"maintainers":[{"name":"davidwood","email":"bitprobe@gmail.com"}],"directories":{}}},"maintainers":[{"name":"davidwood","email":"bitprobe@gmail.com"}],"time":{"modified":"2017-09-11T01:50:54.811Z","created":"2011-05-27T22:31:00.527Z","1.0.0":"2011-05-27T22:31:00.963Z","1.0.1":"2011-05-28T00:07:52.970Z","1.1.0":"2011-06-05T22:47:07.423Z","1.1.2":"2011-08-11T14:32:05.624Z","1.1.3":"2011-11-18T15:41:10.348Z","1.2.0":"2012-04-30T21:41:07.576Z","1.2.1":"2012-05-26T19:55:03.233Z","1.2.2":"2014-04-22T15:32:19.354Z"},"author":{"name":"David Wood","email":"bitprobe@gmail.com"},"repository":{"type":"git","url":"http://github.com/davidwood/node-password-hash.git"},"readme":"# Deprecated: Use [bcrypt](https://github.com/ncb000gt/node.bcrypt.js) or [scrypt](https://github.com/barrysteyn/node-scrypt)\n\n## node-password-hash[![Build Status](https://secure.travis-ci.org/davidwood/node-password-hash.png)](http://travis-ci.org/davidwood/node-password-hash)\n\npassword-hash is a node.js library to simplify use of hashed passwords.\n\nStoring passwords in plain-text is bad.  This library makes the storing of passwords (and subsequent validation of) hashed passwords a bit easier.  \n\npassword-hash provides functions for generating a hashed passwords and verifying a plain-text password against a hashed password.  For a bit of added strength, a random salt is generated when the password is hashed.  The hashed password contains both the cryptographic algorithm that was used as well the salt, so all that is needed to verify a plain-text password is the hashed password itself.\n\n## Installation\n\n    npm install password-hash\n\n## Usage\n\n### generate(password, [options])\n\nGenerates a hash of the required `password` argument.  Hashing behavior can be modified with the optional `options` object:\n\n* `algorithm` - A valid cryptographic algorithm for use with the `crypto.createHmac` function, defaults to 'sha1'.\n* `saltLength` - The length of the salt that will be generated when the password is hashed, defaults to 8.\n* `iterations` - The number of times the hashing algorithm should be applied, defaults to 1.\n\nErrors are thrown if:\n\n* `password` is not a string\n* `options.algorithm` is specified but not a valid cryptographic algorithm\n* `options.saltLength` is specified but not a positive integer\n\nThe hashed password will be in the format `algorithm$salt$hash`.\n\nExample:\n<pre>\n    var passwordHash = require('password-hash');\n\n    var hashedPassword = passwordHash.generate('password123');\n\n    console.log(hashedPassword); // sha1$3I7HRwy7$cbfdac6008f9cab4083784cbd1874f76618d2a97\n</pre>\n\n### verify(password, hashedPassword)\n\nCompares a plain-text password (`password`) to a hashed password (`hashedPassword`) and returns a boolean.  Both arguments are required.\n\nExample:\n<pre>\n    var passwordHash = require('./lib/password-hash');\n\n    var hashedPassword = 'sha1$3I7HRwy7$cbfdac6008f9cab4083784cbd1874f76618d2a97';\n    \n    console.log(passwordHash.verify('password123', hashedPassword)); // true\n    console.log(passwordHash.verify('Password0', hashedPassword)); // false\n</pre>\n\n### isHashed(password)\n\nCheck if a password (`password`) is hashed.  Returns a boolean.\n\nExample:\n<pre>\n    var passwordHash = require('./lib/password-hash');\n\n    var hashedPassword = 'sha1$3I7HRwy7$cbfdac6008f9cab4083784cbd1874f76618d2a97';\n    \n    console.log(passwordHash.isHashed('password123')); // false\n    console.log(passwordHash.isHashed(hashedPassword)); // true\n</pre>\n\n## Salt Generation\n\nnode 0.5.8 introduced `crypto.randomBytes`, which generates cryptographically strong pseudo-random data. If the version of node supports `crypto.randomBytes` it is used to generate the salt, otherwise `Math.random`, which is not cryptographically strong, is used. This is handled transparently within the salt generation function and does not impact the module's API. \n\n## Inspired by\n\npassword-hash is inspired by the password hashing found in [Werkzeug](http://werkzeug.pocoo.org/).\n","homepage":"https://github.com/davidwood/node-password-hash","keywords":["password","hash","utilities","cli"],"bugs":{"url":"https://github.com/davidwood/node-password-hash/issues"},"readmeFilename":"README.md","users":{"friktor":true,"boustanihani":true,"erincinci":true,"jesusgoku":true,"jaredvogt":true,"saravananr":true,"dubbya":true,"hongbo-miao":true,"rocket0191":true,"yonisetiawan":true,"desmondddd":true,"ssljivic":true,"axelrindle":true,"itcorp":true,"abnerlin":true},"_attachments":{},"_etag":"W/\"e7545bdf9c71c4d73446796288eaa0a4\"","_lastModified":"Sun, 27 May 2018 11:56:00 GMT","_cached":true}